sirbot/slack/__init__.py
sirbot/slack/__meta__.py
sirbot/slack/api.py
sirbot/slack/config.yml
sirbot/slack/core.py
sirbot/slack/errors.py
sirbot/slack/message.py
sirbot/slack/sync.py
sirbot/slack/wrapper.py
sirbot/slack/database/__init__.py
sirbot/slack/database/sqlite/__init__.py
sirbot/slack/database/sqlite/channel.py
sirbot/slack/database/sqlite/dispatcher.py
sirbot/slack/database/sqlite/group.py
sirbot/slack/database/sqlite/message.py
sirbot/slack/database/sqlite/update.py
sirbot/slack/database/sqlite/user.py
sirbot/slack/dispatcher/__init__.py
sirbot/slack/dispatcher/action.py
sirbot/slack/dispatcher/command.py
sirbot/slack/dispatcher/dispatcher.py
sirbot/slack/dispatcher/event.py
sirbot/slack/dispatcher/message.py
sirbot/slack/store/__init__.py
sirbot/slack/store/channel.py
sirbot/slack/store/group.py
sirbot/slack/store/store.py
sirbot/slack/store/user.py
sirbot/slack/store/message/__init__.py
sirbot/slack/store/message/action.py
sirbot/slack/store/message/attachment.py
sirbot/slack/store/message/command.py
sirbot/slack/store/message/message.py
sirbot/slack/store/message/store.py
sirbot.slack-0.2.0.dist-info/DESCRIPTION.rst
sirbot.slack-0.2.0.dist-info/METADATA
sirbot.slack-0.2.0.dist-info/RECORD
sirbot.slack-0.2.0.dist-info/WHEEL
sirbot.slack-0.2.0.dist-info/metadata.json
sirbot.slack-0.2.0.dist-info/top_level.txt
