Metadata-Version: 2.0
Name: sirbot.slack
Version: 0.2.0
Summary: Slack plugin for the good Sir Bot a lot
Home-page: https://github.com/pyslackers/sirbot-slack/
Author: pythondev slack community
Author-email: pythondev.slack@gmail.com
License: MIT
Keywords: sirbot,chatbot,bot,slack
Platform: UNKNOWN
Classifier: Development Status :: 2 - Pre-Alpha
Classifier: Intended Audience :: Developers
Classifier: Topic :: Software Development
Classifier: License :: OSI Approved :: MIT License
Classifier: Natural Language :: English
Classifier: Programming Language :: Python :: 3
Classifier: Programming Language :: Python :: 3.5
Classifier: Programming Language :: Python :: 3.6
Classifier: Environment :: Console
Requires-Dist: sir-bot-a-lot (==0.2.0)
Requires-Dist: sirbot.plugins (==0.2.0)
Provides-Extra: dev
Requires-Dist: Sphinx; extra == 'dev'
Requires-Dist: flake8; extra == 'dev'
Requires-Dist: pytest; extra == 'dev'
Requires-Dist: pytest-aiohttp; extra == 'dev'
Requires-Dist: pytest-asyncio; extra == 'dev'
Requires-Dist: pytest-cov; extra == 'dev'
Requires-Dist: pytest-runner; extra == 'dev'
Requires-Dist: recommonmark; extra == 'dev'
